{
  "_fv": 47,
  "_type": "recipe",
  "definition": {
    "recipeType": "Crafting",
    "recipeRetstackSize": 1,
    "group": "mythicsharkocloth",
    "cookingBookCategory": "MISC",
    "xpReward": 0.0,
    "cookingTime": 200,
    "craftingBookCategory": "MISC",
    "recipeShapeless": true,
    "recipeSlots": [
      {
        "value": ""
      },
      {
        "value": ""
      },
      {
        "value": ""
      },
      {
        "value": "CUSTOM:LegendarySharkoCloth"
      },
      {
        "value": "Blocks.GOLD_BLOCK"
      },
      {
        "value": "Blocks.GOLD_BLOCK"
      },
      {
        "value": "Blocks.GOLD_BLOCK"
      },
      {
        "value": ""
      },
      {
        "value": ""
      }
    ],
    "recipeReturnStack": {
      "value": "CUSTOM:MythicSharkoCloth"
    },
    "name": "mythic_sharko_cloth_craft",
    "namespace": "mod"
  }
}