{
  "display": {
    "icon": {
      "item": "allaboutengie:deleted_mod_element"
    },
    "title": {
      "translate": "advancements.mammoth_ban_obtain.title"
    },
    "description": {
      "translate": "advancements.mammoth_ban_obtain.descr"
    },
    "frame": "challenge",
    "show_toast": true,
    "announce_to_chat": true,
    "hidden": false
  },
  "criteria": {
    "mammoth_ban_obtain": {
      "trigger": "minecraft:impossible"
    }
  },
  "rewards": {
    "experience": 60
  },
  "parent": "allaboutengie:immense_ban_obtain"
}