{
  "display": {
    "background": "allaboutengie:textures/screens/aaeadvancementbackgrounddetective.png",
    "icon": {
      "item": "allaboutengie:aae_engie"
    },
    "title": {
      "translate": "advancements.new_world_new_problem.title"
    },
    "description": {
      "translate": "advancements.new_world_new_problem.descr"
    },
    "frame": "task",
    "show_toast": false,
    "announce_to_chat": false,
    "hidden": false
  },
  "criteria": {
    "new_world_new_problem": {
      "trigger": "minecraft:impossible"
    }
  }
}